django_couch/__init__.py
django_couch/context_processors.py
django_couch/generic.py
django_couch/shortcuts.py
django_couch/translit.py
django_couch/admin/__init__.py
django_couch/admin/deprecated.py
django_couch/admin/forms.py
django_couch/admin/urls.py
django_couch/admin/views.py
django_couch/admin/templates/admin/app.html
django_couch/admin/templates/admin/attachment_delete.html
django_couch/admin/templates/admin/base.html
django_couch/admin/templates/admin/document.html
django_couch/admin/templates/admin/document_delete.html
django_couch/admin/templates/admin/documents.html
django_couch/admin/templates/admin/login.html
django_couch/admin/templates/admin/root.html
django_couch/admin/templates/admin/snippets/path.html
django_couch/admin/templates/admin.deprecated/change_list.html
django_couch/admin/templates/admin.deprecated/change_list_results.html
django_couch/admin/templates/admin.deprecated/includes/fieldset.html
django_couch/auth/__init__.py
django_couch/auth/admin.py
django_couch/auth/backend.py
django_couch/auth/forms.py
django_couch/auth/models.py
django_couch/auth/utils.py
django_couch/auth/management/__init__.py
django_couch/auth/management/commands/__init__.py
django_couch/cluster/__init__.py
django_couch/cluster/forms.py
django_couch/cluster/urls.py
django_couch/cluster/views.py
django_couch/cluster/templatetags/__init__.py
django_couch/cluster/templatetags/cluster_extras.py
django_couch/flatpages/__init__.py
django_couch/flatpages/admin.py
django_couch/flatpages/forms.py
django_couch/flatpages/middleware.py
django_couch/flatpages/sitemaps.py
django_couch/management/__init__.py
django_couch/management/commands/__init__.py
django_couch/management/commands/couch.py
django_couch/management/commands/couch_create_admin.py
django_couch/management/commands/couch_init.py
django_couch/management/commands/couch_munin.py
django_couch/management/commands/couch_ping.py
django_couch/sitemaps/__init__.py
django_couch/sitemaps/views.py
django_couch_utils-1.6.6.dist-info/METADATA
django_couch_utils-1.6.6.dist-info/WHEEL
django_couch_utils-1.6.6.dist-info/RECORD
